Workbook
Name DealValue: 'Deal & S&U'!B23
Name EquityPurchasePrice: 'Deal & S&U'!B6
Name CashPerShare: 'Assumptions'!B8
Name ExchangeRatio: 'Assumptions'!B9
Name ImpliedPremium: 'Deal & S&U'!B9
Name Goodwill: 'PPA'!B11
Name NewDebt: 'Assumptions'!B15
Name NewSharesIssued: 'Deal & S&U'!B8
Name ProFormaEPS_Y1: 'Pro Forma IS'!B14
Name Accretion_Y1: 'Accretion-Dilution'!B6
Name Accretion_Y2: 'Accretion-Dilution'!C6
Name Accretion_Y3: 'Accretion-Dilution'!D6
Name BreakevenSynergies: 'Sensitivities'!B3
Name AcquirerOwnership: 'Contribution'!B14
Name TargetOwnership: 'Contribution'!B15

Sheet Cover
A1: Synopsys, Inc. (SNPS) acquires ANSYS, Inc. (ANSS)
A3: Announced | B3: 2024-01-16
A4: Expected close | B4: Pending
A6: Headline
A7: Equity purchase price | B7: ='Deal & S&U'!B6
A8: Implied premium | B8: ='Deal & S&U'!B9
A9: Goodwill created | B9: ='PPA'!B11
A11: Accretion / (dilution) — primary case
A12: Year 1 | B12: ='Accretion-Dilution'!B6
A13: Year 2 | B13: ='Accretion-Dilution'!C6
A14: Year 3 | B14: ='Accretion-Dilution'!D6
A16: Educational project — not investment advice. SEC EDGAR data used per fair-access policy; no SEC or advisor endorsement implied.

Sheet Assumptions
A1: Assumptions (inputs — blue)
A3: Standalone drivers
A4: Acquirer revenue growth | B4: 0.11 | C4: 0.1 | D4: 0.1 | E4: 0.09 | F4: 0.09
A5: Target revenue growth | B5: 0.09 | C5: 0.08 | D5: 0.08 | E5: 0.07 | F5: 0.07
A7: Deal terms (disclosed)
A8: Cash per target share | B8: 197
A9: Exchange ratio | B9: 0.345
A10: Reference acquirer price | B10: 559.96
A11: Target shares outstanding | B11: 87299981
A12: Premium reference price | B12: 303.16
A14: Our deal assumptions
A15: New acquisition debt | B15: 14300000000
A16: New debt rate | B16: 0.05
A17: Cash on hand used | B17: 3048096257
A18: Foregone cash yield | B18: 0.04
A19: Advisory fees | B19: 100000000
A20: Financing fees | B20: 50000000
A21: Intangible step-up | B21: 8000000000
A22: PP&E step-up | B22: 0
A23: Deferred-tax rate on step-ups | B23: 0.21
A24: Marginal tax rate | B24: 0.16
A26: Purchase price accounting — book inputs
A27: Target book equity | B27: 8918797000
A28: Target existing goodwill | B28: 3778128000
A30: Synergy cases (run-rate, pre-tax)
A31: Base (ours) (our case) | B31: 300000000
A32: Conservative (ours) (our case) | B32: 150000000

Sheet Acquirer
A1: Acquirer — standalone
A3: Line ($) | B3: Base | C3: Y1 | D3: Y2 | E3: Y3 | F3: Y4 | G3: Y5
A4: Revenue | B4: 6127436000 | C4: =B4*(1+'Assumptions'!B4) | D4: =C4*(1+'Assumptions'!C4) | E4: =D4*(1+'Assumptions'!D4) | F4: =E4*(1+'Assumptions'!E4) | G4: =F4*(1+'Assumptions'!F4)
A5: Net income | C5: 2.0077744e+09 | D5: 2.2493252e+09 | E5: 2.5164795e+09 | F5: 2.788497e+09 | G5: 3.0863308e+09

Sheet Target
A1: Target — standalone
A3: Line ($) | B3: Base | C3: Y1 | D3: Y2 | E3: Y3 | F3: Y4 | G3: Y5
A4: Revenue | B4: 2544809000 | C4: =B4*(1+'Assumptions'!B5) | D4: =C4*(1+'Assumptions'!C5) | E4: =D4*(1+'Assumptions'!D5) | F4: =E4*(1+'Assumptions'!E5) | G4: =F4*(1+'Assumptions'!F5)
A5: Net income | C5: 7.1355757e+08 | D5: 7.770011e+08 | E5: 8.393138e+08 | F5: 8.9852765e+08 | G5: 9.6196578e+08

Sheet Deal & S&U
A1: Deal — consideration, sources & uses
A3: Consideration
A4: Aggregate cash consideration | B4: ='Assumptions'!B8*'Assumptions'!B11
A5: Aggregate stock consideration | B5: ='Assumptions'!B9*'Assumptions'!B10*'Assumptions'!B11
A6: Equity purchase price | B6: =B4+B5
A7: Total consideration per share | B7: ='Assumptions'!B8+'Assumptions'!B9*'Assumptions'!B10
A8: New shares issued | B8: ='Assumptions'!B9*'Assumptions'!B11
A9: Implied premium | B9: =B7/'Assumptions'!B12-1
A11: Sources
A12: New debt | B12: 14300000000
A13: Cash on hand | B13: 3048096257
A14: Stock issued | B14: 1.6865152e+10
A15: Additional cash | B15: 0
A16: Total sources | B16: =SUM(B12:B15)
A18: Uses
A19: Equity purchase price | B19: 3.4063248e+10
A20: Refinance target debt | B20: 0
A21: Advisory fees | B21: 100000000
A22: Financing fees | B22: 50000000
A23: Total uses | B23: =SUM(B19:B22)

Sheet PPA
A1: Purchase price accounting → goodwill (the plug)
A3: Equity purchase price | B3: ='Deal & S&U'!B6
A4: Target book equity | B4: ='Assumptions'!B27
A5: Less: existing goodwill written off | B5: ='Assumptions'!B28
A6: Identifiable net assets at book | B6: =B4-B5
A7: Intangible step-up | B7: ='Assumptions'!B21
A8: PP&E step-up | B8: ='Assumptions'!B22
A9: Deferred tax liability on step-ups | B9: =(B7+B8)*'Assumptions'!B23
A10: Net identifiable assets | B10: =B6+B7+B8-B9
A11: Goodwill | B11: =B3-B10

Sheet Pro Forma IS
A1: Pro Forma Income Statement (primary synergy case)
A3: Line ($) | B3: Y1 | C3: Y2 | D3: Y3 | E3: Y4 | F3: Y5
A4: Acquirer standalone net income | B4: 2.0077744e+09 | C4: 2.2493252e+09 | D4: 2.5164795e+09 | E4: 2.788497e+09 | F4: 3.0863308e+09
A5: Target standalone net income | B5: 7.1355757e+08 | C5: 7.770011e+08 | D5: 8.393138e+08 | E5: 8.9852765e+08 | F5: 9.6196578e+08
A6: Less: incremental interest (after-tax) | B6: 600600000 | C6: 600600000 | D6: 600600000 | E6: 600600000 | F6: 600600000
A7: Less: foregone interest income (after-tax) | B7: 1.0241603e+08 | C7: 1.0241603e+08 | D7: 1.0241603e+08 | E7: 1.0241603e+08 | F7: 1.0241603e+08
A8: Less: incremental D&A (after-tax) | B8: 672000000 | C8: 672000000 | D8: 672000000 | E8: 672000000 | F8: 672000000
A9: Plus: synergies (after-tax) | B9: 126000000 | C9: 189000000 | D9: 252000000 | E9: 252000000 | F9: 252000000
A10: Pro forma net income | B10: =B4+B5-B6-B7-B8+B9 | C10: =C4+C5-C6-C7-C8+C9 | D10: =D4+D5-D6-D7-D8+D9 | E10: =E4+E5-E6-E7-E8+E9 | F10: =F4+F5-F6-F7-F8+F9
A11: Acquirer standalone shares | B11: 155944000 | C11: 155944000 | D11: 155944000 | E11: 155944000 | F11: 155944000
A12: New shares issued | B12: ='Deal & S&U'!B8 | C12: ='Deal & S&U'!B8 | D12: ='Deal & S&U'!B8 | E12: ='Deal & S&U'!B8 | F12: ='Deal & S&U'!B8
A13: Pro forma shares | B13: =B11+B12 | C13: =C11+C12 | D13: =D11+D12 | E13: =E11+E12 | F13: =F11+F12
A14: Pro forma EPS | B14: =B10/B13 | C14: =C10/C13 | D14: =D10/D13 | E14: =E10/E13 | F14: =F10/F13

Sheet Pro Forma BS
A1: Pro Forma Balance Sheet (engine-computed, invariant-checked)
A3: Line ($) | B3: FY2025E | C3: FY2026E | D3: FY2027E | E3: FY2028E | F3: FY2029E
A4: Cash & equivalents | B4: 4.787964e+09 | C4: 7.099727e+09 | D4: 9.6834241e+09 | E4: 1.2563431e+10 | F4: 1.5747689e+10
A5: Goodwill | B5: 2.6051429e+10 | C5: 2.6051429e+10 | D5: 2.6051429e+10 | E5: 2.6051429e+10 | F5: 2.6051429e+10
A6: Total assets | B6: 4.5341886e+10 | C6: 4.7604398e+10 | D6: 5.0135343e+10 | E6: 5.2938063e+10 | F6: 5.6039856e+10
A7: Total liabilities | B7: 1.5578259e+10 | C7: 1.5591446e+10 | D7: 1.5605911e+10 | E7: 1.5620135e+10 | F7: 1.5635597e+10
A8: Total stockholders' equity | B8: 2.9763627e+10 | C8: 3.2012952e+10 | D8: 3.4529432e+10 | E8: 3.7317929e+10 | F8: 4.0404259e+10

Sheet Accretion-Dilution
A1: Accretion / (Dilution) — primary synergy case
A3: Line | B3: Y1 | C3: Y2 | D3: Y3 | E3: Y4 | F3: Y5
A4: Acquirer standalone EPS | B4: ='Pro Forma IS'!B4/'Pro Forma IS'!B11 | C4: ='Pro Forma IS'!C4/'Pro Forma IS'!C11 | D4: ='Pro Forma IS'!D4/'Pro Forma IS'!D11 | E4: ='Pro Forma IS'!E4/'Pro Forma IS'!E11 | F4: ='Pro Forma IS'!F4/'Pro Forma IS'!F11
A5: Pro forma EPS | B5: ='Pro Forma IS'!B14 | C5: ='Pro Forma IS'!C14 | D5: ='Pro Forma IS'!D14 | E5: ='Pro Forma IS'!E14 | F5: ='Pro Forma IS'!F14
A6: Accretion / (dilution) | B6: =B5/B4-1 | C6: =C5/C4-1 | D6: =D5/D4-1 | E6: =E5/E4-1 | F6: =F5/F4-1

Sheet Contribution
A1: Contribution vs. pro forma ownership
A3: Contribution ($)
A4: Acquirer revenue | B4: 6.801454e+09
A5: Target revenue | B5: 2773841810
A6: Acquirer EBITDA | B6: 2.516538e+09
A7: Target EBITDA | B7: 9.8471384e+08
A8: Acquirer net income | B8: 2.0077744e+09
A9: Target net income | B9: 7.1355757e+08
A11: Pro forma ownership
A12: Acquirer existing shares | B12: 155944000
A13: New shares issued to target | B13: ='Deal & S&U'!B8
A14: Acquirer ownership | B14: =B12/(B12+B13)
A15: Target ownership | B15: =B13/(B12+B13)

Sheet Sensitivities
A1: Sensitivities — premium × synergies (Year-1 A/D)
A3: Breakeven synergies (Year-1 A/D = 0) | B3: 1.2490871e+09
A6: premium \ synergies | B6: 0 | C6: 2000000000 | D6: 4000000000 | E6: 6000000000 | F6: 8000000000
A7: 0.1 | B7: -0.3511928 | C7: 0.35010777 | D7: =B7+(C7-B7)/(C6-B6)*(D6-B6) | E7: =B7+(C7-B7)/(C6-B6)*(E6-B6) | F7: =B7+(C7-B7)/(C6-B6)*(F6-B6)
A8: 0.2 | B8: -0.39759411 | C8: 0.30370646 | D8: =B8+(C8-B8)/(C6-B6)*(D6-B6) | E8: =B8+(C8-B8)/(C6-B6)*(E6-B6) | F8: =B8+(C8-B8)/(C6-B6)*(F6-B6)
A9: 0.3 | B9: -0.44399542 | C9: 0.25730515 | D9: =B9+(C9-B9)/(C6-B6)*(D6-B6) | E9: =B9+(C9-B9)/(C6-B6)*(E6-B6) | F9: =B9+(C9-B9)/(C6-B6)*(F6-B6)
A10: 0.4 | B10: -0.49039673 | C10: 0.21090384 | D10: =B10+(C10-B10)/(C6-B6)*(D6-B6) | E10: =B10+(C10-B10)/(C6-B6)*(E6-B6) | F10: =B10+(C10-B10)/(C6-B6)*(F6-B6)
A11: 0.5 | B11: -0.53679804 | C11: 0.16450253 | D11: =B11+(C11-B11)/(C6-B6)*(D6-B6) | E11: =B11+(C11-B11)/(C6-B6)*(E6-B6) | F11: =B11+(C11-B11)/(C6-B6)*(F6-B6)

Sheet Precedents
A1: Precedent Transactions (premiums / multiples — cited)
A3: Date | B3: Acquirer | C3: Target | D3: EV | E3: EV/Rev | F3: EV/EBITDA | G3: Source
A4: 2023-11-22 | B4: Broadcom | C4: VMware | D4: 69000 | E4: 7.4 | F4: 20.6 | G4: Broadcom/VMware DEFM14A & press release, announced 2022-05-26, closed 2023-11-22; EV ~$69B incl. debt
A5: 2022-09-15 | B5: Adobe | C5: Figma | D5: 20000 | E5: 50 | G5: Adobe/Figma press release 2022-09-15 (deal later terminated 2023-12); ~$20B, ~50x ARR
A6: 2022-10-27 | B6: Elon Musk / investors | C6: Twitter | D6: 44000 | E6: 7.3 | G6: Twitter merger proxy 2022; $54.20/share, ~$44B EV
A7: 2022-01-18 | B7: Microsoft | C7: Activision Blizzard | D7: 68700 | E7: 7.9 | F7: 18.9 | G7: Microsoft/Activision DEFM14A, $95.00/share, ~$68.7B EV, closed 2023-10
A8: 2023-04-27 | B8: Qualtrics | C8: Silver Lake/CPPIB | D8: 12500 | E8: 7 | G8: Qualtrics take-private DEFM14A 2023; $18.15/share, ~$12.5B EV
A9: 2021-04-15 | B9: Thoma Bravo | C9: Proofpoint | D9: 12300 | E9: 10.9 | G9: Proofpoint DEFM14A 2021; $176.00/share, ~$12.3B EV
A10: 2020-12-01 | B10: Salesforce | C10: Slack | D10: 27700 | E10: 26 | G10: Salesforce/Slack S-4 2020-2021; ~$27.7B, ~26x revenue
A11: 2022-03-08 | B11: Google | C11: Mandiant | D11: 5400 | E11: 9 | G11: Google/Mandiant press release 2022-03-08; $23.00/share, ~$5.4B
A12: 2016-06-13 | B12: Microsoft | C12: LinkedIn | D12: 26200 | E12: 7.2 | F12: 24 | G12: Microsoft/LinkedIn merger proxy 2016; $196.00/share, ~$26.2B EV (Qatalyst advised LinkedIn)

Sheet Fairness Comparison
A1: Fairness Comparison — advisor ranges vs. our reproduction
A3: Advisor | B3: Method | C3: Disclosed low | D3: Disclosed high | E3: Our low | F3: Our high | G3: Disclosed mid | H3: Our mid | I3: Overlap %
A4: Qatalyst Partners | B4: Discounted Cash Flow | C4: 160.25 | D4: 496.04 | E4: 342.43831 | F4: 555.02281 | G4: =(C4+D4)/2 | H4: =(E4+F4)/2 | I4: =MAX(0,MIN(1,(MIN(D4,F4)-MAX(C4,E4))/(D4-C4)))
A5: Qatalyst Partners | B5: Selected Companies | C5: 198.32 | D5: 340.71 | E5: 227.66328 | F5: 364.26125 | G5: =(C5+D5)/2 | H5: =(E5+F5)/2 | I5: =MAX(0,MIN(1,(MIN(D5,F5)-MAX(C5,E5))/(D5-C5)))
A6: Qatalyst Partners | B6: Selected Transactions | C6: 199.97 | D6: 319.88 | E6: 227.66328 | F6: 364.26125 | G6: =(C6+D6)/2 | H6: =(E6+F6)/2 | I6: =MAX(0,MIN(1,(MIN(D6,F6)-MAX(C6,E6))/(D6-C6)))
